pcsaft.cpython-38-x86_64-linux-gnu.so
pcsaft-1.4.1.dist-info/top_level.txt
pcsaft-1.4.1.dist-info/WHEEL
pcsaft-1.4.1.dist-info/METADATA
pcsaft-1.4.1.dist-info/RECORD
pcsaft-1.4.1.dist-info/LICENSE
