Metadata-Version: 2.1
Name: pcsaft
Version: 1.4.1
Summary: The PC-SAFT equation of state, including dipole, association and ion terms.
Home-page: https://github.com/zmeri/PC-SAFT
Author: Zach Baird
Classifier: Programming Language :: Python :: 3
Classifier: Programming Language :: C++
Classifier: License :: OSI Approved :: GNU General Public License v3 (GPLv3)
Classifier: Operating System :: Microsoft :: Windows :: Windows 10
Classifier: Operating System :: POSIX :: Linux
Classifier: Operating System :: MacOS
License-File: LICENSE
